<?xml version="1.0" encoding="utf-8" ?>
<dwsync>
<file name="variables.less" server="fs.mis.kuas.edu.tw//www/" local="131268731223948688" remote="131268453600000000" Dst="0" />
<file name="stacked.less" server="fs.mis.kuas.edu.tw//www/" local="131268731223878624" remote="131268453600000000" Dst="0" />
<file name="screen-reader.less" server="fs.mis.kuas.edu.tw//www/" local="131268731223878624" remote="131268453600000000" Dst="0" />
<file name="rotated-flipped.less" server="fs.mis.kuas.edu.tw//www/" local="131268731223838608" remote="131268453600000000" Dst="0" />
<file name="path.less" server="fs.mis.kuas.edu.tw//www/" local="131268731223788558" remote="131268453600000000" Dst="0" />
<file name="mixins.less" server="fs.mis.kuas.edu.tw//www/" local="131268731223758548" remote="131268453600000000" Dst="0" />
<file name="list.less" server="fs.mis.kuas.edu.tw//www/" local="131268731223708508" remote="131268453600000000" Dst="0" />
<file name="larger.less" server="fs.mis.kuas.edu.tw//www/" local="131268731223678634" remote="131268453600000000" Dst="0" />
<file name="icons.less" server="fs.mis.kuas.edu.tw//www/" local="131268731223668473" remote="131268453600000000" Dst="0" />
<file name="font-awesome.less" server="fs.mis.kuas.edu.tw//www/" local="131268731223632040" remote="131268453600000000" Dst="0" />
<file name="fixed-width.less" server="fs.mis.kuas.edu.tw//www/" local="131268731223602020" remote="131268453600000000" Dst="0" />
<file name="core.less" server="fs.mis.kuas.edu.tw//www/" local="131268731223597016" remote="131268453600000000" Dst="0" />
<file name="bordered-pulled.less" server="fs.mis.kuas.edu.tw//www/" local="131268731223556987" remote="131268453600000000" Dst="0" />
<file name="animated.less" server="fs.mis.kuas.edu.tw//www/" local="131268731223516975" remote="131268453600000000" Dst="0" />
</dwsync>